[
    {
      "question": "Savings enable economic growth by providing capital for investments in productive ventures.",
      "answer": "True"
    },
    {
      "question": "Collaboration in business ventures leads to less innovation.",
      "answer": "False"
    },
    {
      "question": "Excessive consumer borrowing without saving can lead to economic crises.",
      "answer": "True"
    },
    {
      "question": "The core of economic value is spending money on consumption.",
      "answer": "False"
    },
    {
      "question": "Countries that prioritize savings often achieve higher economic resilience.",
      "answer": "True"
    },
    {
      "question": "High levels of debt lead to sustained economic growth in the long run.",
      "answer": "False"
    }
  ]
  