{
    "SingleLineAnswers": [
      {
        "question": "What triggered the collapse of the Fish Reserve Notes in Sinopia?",
        "answer": "Over-issuing of currency and unsustainable fiscal policies."
      },
      {
        "question": "Which country faced hyperinflation in the 1920s?",
        "answer": "Germany."
      },
      {
        "question": "What caused Zimbabwe’s hyperinflation in the 2000s?",
        "answer": "Excessive money printing and economic mismanagement."
      },
      {
        "question": "What is capital flight?",
        "answer": "The movement of wealth abroad during economic crisis to safer economies."
      },
      {
        "question": "How did the U.S. respond to stagflation in the 1970s?",
        "answer": "By raising interest rates and controlling prices."
      },
      {
        "question": "What was the main cause of the Great Depression?",
        "answer": "Stock market crash and banking failures."
      },
      {
        "question": "What key factor contributed to Japan’s post-WWII economic recovery?",
        "answer": "Focus on technological innovation and quality manufacturing."
      },
      {
        "question": "How did Russia’s privatization process in the 1990s affect its economy?",
        "answer": "It led to asset stripping and corruption."
      },
      {
        "question": "What was Argentina’s inflation rate in the late 1980s?",
        "answer": "3,000% annually."
      },
      {
        "question": "What helped South Korea transition into an industrialized economy?",
        "answer": "Education, infrastructure development, and industrial output."
      }
    ]
  }
  